swiss_rss/__init__.py
swiss_rss/web_feeds.py
swiss_rss/web_feeds_test.py
swiss_rss/favicons/__init__.py
swiss_rss/favicons/favicon_parser.py
swiss_rss/favicons/favicon_parser_test.py
swiss_rss/opml/__init__.py
swiss_rss/opml/opml_parser.py
swiss_rss/opml/opml_parser_test.py
swiss_rss/timestamps/__init__.py
swiss_rss/timestamps/timestamp_parser.py
swiss_rss/timestamps/timestamp_parser_test.py
swiss_rss-0.1.2.dist-info/METADATA
swiss_rss-0.1.2.dist-info/WHEEL
swiss_rss-0.1.2.dist-info/licenses/LICENSE
swiss_rss-0.1.2.dist-info/RECORD
