Metadata-Version: 2.4
Name: swiss-rss
Version: 0.1.2
Summary: RSS web feeds swiss army knife
Project-URL: Homepage, https://github.com/aluxian/swiss-rss
Project-URL: Repository, https://github.com/aluxian/swiss-rss.git
Project-URL: Issues, https://github.com/aluxian/swiss-rss/issues
Project-URL: Changelog, https://github.com/aluxian/swiss-rss/releases
Author: Alexandru Rosianu
License-Expression: MIT
License-File: LICENSE
Keywords: atom,feed,parser,rss,syndication,web
Classifier: Development Status :: 4 - Beta
Classifier: Intended Audience :: Developers
Classifier: License :: OSI Approved :: MIT License
Classifier: Operating System :: OS Independent
Classifier: Programming Language :: Python :: 3
Classifier: Programming Language :: Python :: 3.12
Classifier: Topic :: Internet :: WWW/HTTP :: Dynamic Content :: News/Diary
Classifier: Topic :: Software Development :: Libraries :: Python Modules
Requires-Python: >=3.12
Requires-Dist: aiohttp>=3.10.10
Requires-Dist: beautifulsoup4>=4.12.3
Requires-Dist: cairosvg>=2.7.1
Requires-Dist: loguru>=0.7.3
Requires-Dist: lxml>=5.1.0
Requires-Dist: pillow>=10.2.0
Requires-Dist: requests>=2.32.3
